essentia_sia_api-0.0.1a0.dist-info/METADATA
essentia_sia_api-0.0.1a0.dist-info/RECORD
essentia_sia_api-0.0.1a0.dist-info/WHEEL
essentia_sia_api-0.0.1a0.dist-info/top_level.txt
sia/__init__.py
sia/sia.py
sia/constants/__init__.py
sia/constants/consensus.py
sia/constants/daemon.py
sia/constants/file.py
sia/constants/gateway.py
sia/constants/host.py
sia/constants/hostdb.py
sia/constants/http.py
sia/constants/miner.py
sia/constants/renter.py
sia/constants/wallet.py
sia/endpoints/__init__.py
sia/endpoints/consensus.py
sia/endpoints/daemon.py
sia/endpoints/file.py
sia/endpoints/gateway.py
sia/endpoints/host.py
sia/endpoints/hostdb.py
sia/endpoints/miner.py
sia/endpoints/renter.py
sia/endpoints/wallet.py
sia/errors/__init__.py
sia/errors/http.py
sia/mixins/__init__.py
sia/mixins/http.py
tests/__init__.py
